{
  "articles": [
    {
      "id": "Market-Analysis-bitcoin-2026",
      "title": "Phân Tích Chu Kỳ & Trạng Thái Thị Trường Bitcoin (2025-2026)",
      "description": "Phân tích chuyên sâu về sự chuyển đổi cấu trúc thị trường Bitcoin",
      "excerpt": "## 1. Tổng Quan Vĩ Mô",
      "url": "/learn/2026/03/03/Market-Analysis-bitcoin-2026.html",
      "date": "2026-03-03",
      "author": "Bitcoin PeakDip Research",
      "category": "General",
      "reading_time": 15,
      "level": "Advanced",
      "icon": "chart-line",
      "featured": false
    },
    {
      "id": "EWS-Signal-Snapshot",
      "title": "EWS Signal Snapshot - February 28, 2026",
      "description": "Local Top Signal detection with whale advance analysis",
      "excerpt": "# EWS Signal Snapshot - February 28, 2026\n## Local Top Signal · Whale Advance",
      "url": "/learn/2026/03/02/EWS-Signal-Snapshot.html",
      "date": "2026-03-02",
      "author": "Bitcoin PeakDip Team",
      "category": "signals",
      "reading_time": 5,
      "level": "Intermediate",
      "icon": "bell",
      "featured": false
    },
    {
      "id": "The-Influence-of-the-Middle-East-Region-on-the-Cryptocurrency-Market",
      "title": "Ảnh Hưởng Của Khu Vực Trung Đông Đến Thị Trường Tiền Điện Tử",
      "description": "Phân tích chuyên sâu về tác động của địa chính trị Trung Đông lên thị trường tiền điện tử, bao gồm xung đột, dòng vốn và chiến lược giao dịch.",
      "excerpt": "# Ảnh Hưởng Của Khu Vực Trung Đông Đến Thị Trường Tiền Điện Tử",
      "url": "/learn/2026/03/02/The-Influence-of-the-Middle-East-Region-on-the-Cryptocurrency-Market.html",
      "date": "2026-03-02",
      "author": "Bitcoin PeakDip Team",
      "category": "Market Analysis",
      "reading_time": 8,
      "level": "Intermediate",
      "icon": "globe-asia",
      "featured": false
    },
    {
      "id": "BTC_Market_Cycles",
      "title": "Bitcoin Market Cycles Through ATH History",
      "description": "Comprehensive analysis of Bitcoin's ATH milestones across different market cycles from 2013 to 2025, with insights on halving events and institutional adoption",
      "excerpt": "# Tóm Tắt: Hành Trình Các ATH Của Bitcoin Qua Các Chu Kỳ",
      "url": "/learn/2026/02/28/BTC_Market_Cycles.html",
      "date": "2026-02-28",
      "author": "Bitcoin PeakDip Team",
      "category": "Market Analysis",
      "reading_time": 8,
      "level": "Intermediate",
      "icon": "chart-line",
      "featured": false
    },
    {
      "id": "strategy-guide-check",
      "title": "8 Trading Strategies Explained",
      "description": "Deep dive into all trading strategies: RECLAIM_FAILURE, MOMENTUM_BREAKDOWN, and more.",
      "excerpt": "## Overview",
      "url": "/learn/2026/02/27/strategy-guide-check.html",
      "date": "2026-02-27",
      "author": "Bitcoin PeakDip Team",
      "category": "strategies",
      "reading_time": 15,
      "level": "Intermediate",
      "icon": "chess-knight",
      "featured": false
    },
    {
      "id": "strategy-guide",
      "title": "8 Trading Strategies Explained",
      "description": "Deep dive into all trading strategies: RECLAIM_FAILURE, MOMENTUM_BREAKDOWN, and more.",
      "excerpt": "## Overview",
      "url": "/learn/2026/02/25/strategy-guide.html",
      "date": "2026-02-25",
      "author": "Bitcoin PeakDip Team",
      "category": "strategies",
      "reading_time": 15,
      "level": "Intermediate",
      "icon": "chess-knight",
      "featured": false
    },
    {
      "id": "SignalActivation",
      "title": "Cảnh báo kích hoạt vùng đỉnh (Peak Area) - Tín hiệu từ Shark và Whale",
      "description": "Cảnh báo kích hoạt vùng đỉnh Bitcoin từ các tín hiệu Shark và Whale. Hiệu lực trong 7 ngày, chờ tín hiệu xác nhận [2] để giao dịch.",
      "excerpt": "## 📡 **CẢNH BÁO KÍCH HOẠT VÙNG ĐỈNH (PEAK AREA)**",
      "url": "/learn/2026/02/16/SignalActivation.html",
      "date": "2026-02-16",
      "author": "Bitcoin PeakDip Team",
      "category": "General",
      "reading_time": 3,
      "level": "Intermediate",
      "icon": "satellite-dish",
      "featured": true
    }
  ],
  "metadata": {
    "last_updated": "2026-03-04T11:09:01+07:00",
    "total": 7,
    "version": "1.12.33",
    "build_timestamp": 1772597341853,
    "build_date": "2026-03-04",
    "build_time": "11:09:01"
  },
  "stats": {
    "new_articles_count": 6,
    "new_articles": [
      {
        "id": "Market-Analysis-bitcoin-2026",
        "title": "Phân Tích Chu Kỳ & Trạng Thái Thị Trường Bitcoin (2025-2026)",
        "url": "/learn/2026/03/03/Market-Analysis-bitcoin-2026.html",
        "date": "2026-03-03",
        "reading_time": 15,
        "level": "Advanced"
      },
      {
        "id": "EWS-Signal-Snapshot",
        "title": "EWS Signal Snapshot - February 28, 2026",
        "url": "/learn/2026/03/02/EWS-Signal-Snapshot.html",
        "date": "2026-03-02",
        "reading_time": 5,
        "level": "Intermediate"
      },
      {
        "id": "The-Influence-of-the-Middle-East-Region-on-the-Cryptocurrency-Market",
        "title": "Ảnh Hưởng Của Khu Vực Trung Đông Đến Thị Trường Tiền Điện Tử",
        "url": "/learn/2026/03/02/The-Influence-of-the-Middle-East-Region-on-the-Cryptocurrency-Market.html",
        "date": "2026-03-02",
        "reading_time": 8,
        "level": "Intermediate"
      },
      {
        "id": "BTC_Market_Cycles",
        "title": "Bitcoin Market Cycles Through ATH History",
        "url": "/learn/2026/02/28/BTC_Market_Cycles.html",
        "date": "2026-02-28",
        "reading_time": 8,
        "level": "Intermediate"
      },
      {
        "id": "strategy-guide-check",
        "title": "8 Trading Strategies Explained",
        "url": "/learn/2026/02/27/strategy-guide-check.html",
        "date": "2026-02-27",
        "reading_time": 15,
        "level": "Intermediate"
      },
      {
        "id": "strategy-guide",
        "title": "8 Trading Strategies Explained",
        "url": "/learn/2026/02/25/strategy-guide.html",
        "date": "2026-02-25",
        "reading_time": 15,
        "level": "Intermediate"
      }
    ],
    "categories": {
      "General": 2,
      "signals": 1,
      "Market Analysis": 2,
      "strategies": 2
    },
    "levels": {
      "Beginner": 0,
      "Intermediate": 6,
      "Advanced": 1
    },
    "featured_count": 1
  }
}